{
    "name": "Hatches\\Http\\Middleware\\RedirectIfAuthenticated",
    "line": 7,
    "short_desc": "",
    "long_desc": "",
    "hint": null,
    "tags": [],
    "namespace": "Hatches\\Http\\Middleware",
    "file": "app\/Http\/Middleware\/RedirectIfAuthenticated.php",
    "hash": "17d6dcb583540d3eb01391da9d473d13e7394e86",
    "parent": null,
    "modifiers": 0,
    "is_trait": false,
    "is_interface": false,
    "aliases": {
        "Closure": "Closure",
        "Guard": "Illuminate\\Contracts\\Auth\\Guard",
        "RedirectResponse": "Illuminate\\Http\\RedirectResponse"
    },
    "errors": [],
    "interfaces": [],
    "traits": [],
    "properties": [],
    "methods": {
        "__construct": {
            "name": "__construct",
            "line": 22,
            "short_desc": "Create a new filter instance.",
            "long_desc": "",
            "hint": [
                [
                    "void",
                    false
                ]
            ],
            "hint_desc": "",
            "tags": [],
            "modifiers": "1",
            "is_by_ref": "",
            "exceptions": [],
            "errors": [],
            "parameters": {
                "auth": {
                    "name": "auth",
                    "line": 22,
                    "short_desc": "",
                    "long_desc": null,
                    "hint": [
                        [
                            "Illuminate\\Contracts\\Auth\\Guard",
                            false
                        ]
                    ],
                    "tags": [],
                    "modifiers": "Guard",
                    "default": null,
                    "is_by_ref": false
                }
            }
        },
        "handle": {
            "name": "handle",
            "line": 34,
            "short_desc": "Handle an incoming request.",
            "long_desc": "",
            "hint": [
                [
                    "mixed",
                    false
                ]
            ],
            "hint_desc": "",
            "tags": [],
            "modifiers": "1",
            "is_by_ref": "",
            "exceptions": [],
            "errors": [],
            "parameters": {
                "request": {
                    "name": "request",
                    "line": 34,
                    "short_desc": "",
                    "long_desc": null,
                    "hint": [
                        [
                            "\\Illuminate\\Http\\Request",
                            false
                        ]
                    ],
                    "tags": [],
                    "modifiers": "",
                    "default": null,
                    "is_by_ref": false
                },
                "next": {
                    "name": "next",
                    "line": 34,
                    "short_desc": "",
                    "long_desc": null,
                    "hint": [
                        [
                            "Closure",
                            false
                        ]
                    ],
                    "tags": [],
                    "modifiers": "Closure",
                    "default": null,
                    "is_by_ref": false
                }
            }
        }
    },
    "constants": []
}